{
  "records": [
    {
      "album": "Europe",
      "file": "IMG_1709.JPG",
      "date": "2009-09-23T10:46:23.000Z",
      "lat": 52.202545,
      "lng": 0.131237,
      "world": [
        128.0933240888889,
        84.32618585868855
      ],
      "politics": {
        "country": "United Kingdom",
        "city": "Cambridge"
      },
      "id": 0
    },
    {
      "album": "Europe",
      "file": "IMG_1879.JPG",
      "date": "2009-10-02T13:28:44.000Z",
      "lat": 51.504307,
      "lng": -0.120978,
      "world": [
        127.9139712,
        85.13006744017842
      ],
      "politics": {
        "country": "United Kingdom"
      },
      "id": 1
    },
    {
      "album": "Random",
      "file": "IMG_2497.JPG",
      "date": "2010-01-16T20:41:58.000Z",
      "lat": 52.205585000000006,
      "lng": 0.117378,
      "world": [
        128.0834688,
        84.32265844695976
      ],
      "politics": {
        "country": "United Kingdom",
        "city": "Cambridge"
      },
      "id": 2
    },
    {
      "album": "Europe",
      "file": "IMG_2693.JPG",
      "date": "2010-01-24T10:54:34.000Z",
      "lat": 55.947685,
      "lng": -3.1917,
      "world": [
        125.73034666666666,
        79.78317379586329
      ],
      "politics": {
        "country": "United Kingdom",
        "city": "Edinburgh"
      },
      "id": 3
    },
    {
      "album": "Europe",
      "file": "IMG_2929.JPG",
      "date": "2010-02-13T11:04:30.000Z",
      "lat": 50.087521,
      "lng": 14.420843,
      "world": [
        138.25482168888888,
        86.72415020144432
      ],
      "politics": {
        "country": "Czech Republic",
        "city": "Prague"
      },
      "id": 4
    },
    {
      "album": "Europe",
      "file": "IMG_3530.JPG",
      "date": "2010-03-15T12:21:10.000Z",
      "lat": 41.88937,
      "lng": 12.49053,
      "world": [
        136.88215466666668,
        95.13733050878578
      ],
      "politics": {
        "country": "Italy",
        "city": "Roma"
      },
      "id": 5
    },
    {
      "album": "Europe",
      "file": "IMG_3767.JPG",
      "date": "2010-03-17T11:00:44.000Z",
      "lat": 43.772778,
      "lng": 11.255659,
      "world": [
        136.00402417777778,
        93.31084144564653
      ],
      "politics": {
        "country": "Italy",
        "city": "Firenze"
      },
      "id": 6
    },
    {
      "album": "Europe",
      "file": "IMG_3930.JPG",
      "date": "2010-03-18T12:47:21.000Z",
      "lat": 45.438061,
      "lng": 12.335887,
      "world": [
        136.7721863111111,
        91.6473706492452
      ],
      "politics": {
        "country": "Italy",
        "city": "Venezia"
      },
      "id": 7
    },
    {
      "album": "Europe",
      "file": "IMG_4207.JPG",
      "date": "2010-03-21T13:38:27.000Z",
      "lat": 40.750153,
      "lng": 14.487619,
      "world": [
        138.30230684444444,
        96.21603160070137
      ],
      "politics": {
        "country": "Italy"
      },
      "id": 8
    },
    {
      "album": "Random",
      "file": "IMG_4444.JPG",
      "date": "2010-04-02T21:27:35.000Z",
      "lat": 3.156478,
      "lng": 101.713638,
      "world": [
        200.32969813333335,
        125.75425715903317
      ],
      "politics": {
        "country": "Malaysia",
        "city": "Kuala Lumpur"
      },
      "id": 9
    },
    {
      "album": "Europe",
      "file": "IMG_5732.JPG",
      "date": "2010-05-02T14:57:28.000Z",
      "lat": 59.327995,
      "lng": 18.073475,
      "world": [
        140.85224888888888,
        75.28849158443775
      ],
      "politics": {
        "country": "Sweden",
        "city": "Stockholm"
      },
      "id": 10
    },
    {
      "album": "Random",
      "file": "IMG_6530.JPG",
      "date": "2010-06-17T05:19:39.000Z",
      "lat": 52.206108,
      "lng": 0.114702,
      "world": [
        128.08156586666666,
        84.32205156857228
      ],
      "politics": {
        "country": "United Kingdom",
        "city": "Cambridge"
      },
      "id": 11
    },
    {
      "album": "Europe",
      "file": "IMG_6718.JPG",
      "date": "2010-06-22T14:12:00.000Z",
      "lat": 52.358803,
      "lng": 4.883401,
      "world": [
        131.47264071111113,
        84.14456104689864
      ],
      "politics": {
        "country": "Netherlands",
        "city": "Amsterdam"
      },
      "id": 12
    },
    {
      "album": "Europe",
      "file": "IMG_6889.JPG",
      "date": "2010-06-24T11:13:51.000Z",
      "lat": 41.391861,
      "lng": 2.1650359999999997,
      "world": [
        129.53958115555557,
        95.61073361372894
      ],
      "politics": {
        "country": "Spain",
        "city": "Barcelona"
      },
      "id": 13
    },
    {
      "album": "Europe",
      "file": "IMG_7369.JPG",
      "date": "2010-06-30T10:46:14.000Z",
      "lat": 48.858234,
      "lng": 2.2945119999999997,
      "world": [
        129.63165297777778,
        88.06950512126788
      ],
      "politics": {
        "country": "France",
        "city": "Paris"
      },
      "id": 14
    },
    {
      "album": "Random",
      "file": "IMG_0568.JPG",
      "date": "2012-03-26T10:15:33.000Z",
      "lat": -13.164768,
      "lng": -72.545197,
      "world": [
        76.41230435555556,
        137.44508911916904
      ],
      "politics": {
        "country": "Peru"
      },
      "id": 15
    },
    {
      "album": "Random",
      "file": "IMG_1138.JPG",
      "date": "2012-04-03T14:18:28.000Z",
      "lat": -25.681496000000003,
      "lng": -54.440872,
      "world": [
        89.28649102222222,
        146.90653300596617
      ],
      "politics": {
        "country": "Brazil",
        "city": "Foz do Iguaçu"
      },
      "id": 16
    },
    {
      "album": "Random",
      "file": "IMG_1376.JPG",
      "date": "2012-04-06T08:37:48.000Z",
      "lat": -22.752811,
      "lng": -41.884169,
      "world": [
        98.21570204444444,
        144.6226020414295
      ],
      "politics": {
        "country": "Brazil",
        "city": "Armação dos Búzios"
      },
      "id": 17
    },
    {
      "album": "Thailand",
      "file": "IMG_2501.JPG",
      "date": "2012-11-01T15:56:52.000Z",
      "lat": 7.741789,
      "lng": 98.771268,
      "world": [
        198.23734613333335,
        122.47789901942623
      ],
      "politics": {
        "country": "Thailand",
        "city": "Tambon Ao Nang"
      },
      "id": 18
    },
    {
      "album": "Thailand",
      "file": "IMG_2666.JPG",
      "date": "2012-11-02T12:17:27.000Z",
      "lat": 7.761717,
      "lng": 98.759575,
      "world": [
        198.2290311111111,
        122.46359730478756
      ],
      "politics": {
        "country": "Thailand",
        "city": "Tambon Ao Nang"
      },
      "id": 19
    },
    {
      "album": "Thailand",
      "file": "IMG_3796.JPG",
      "date": "2012-11-06T14:08:16.000Z",
      "lat": 18.804978,
      "lng": 98.921603,
      "world": [
        198.34425102222224,
        114.38081438929046
      ],
      "politics": {
        "country": "Thailand"
      },
      "id": 20
    },
    {
      "album": "India",
      "file": "IMG_2525.JPG",
      "date": "2013-03-16T14:32:53.000Z",
      "lat": 28.656533,
      "lng": 77.23803,
      "world": [
        182.92482133333334,
        106.71510147690879
      ],
      "politics": {
        "country": "India",
        "city": "New Delhi"
      },
      "id": 21
    },
    {
      "album": "India",
      "file": "IMG_2630.JPG",
      "date": "2013-03-16T16:45:46.000Z",
      "lat": 28.650053,
      "lng": 77.2285,
      "world": [
        182.91804444444443,
        106.72035253548155
      ],
      "politics": {
        "country": "India",
        "city": "New Delhi"
      },
      "id": 22
    },
    {
      "album": "India",
      "file": "IMG_2843.JPG",
      "date": "2013-03-23T14:27:25.000Z",
      "lat": 28.657171,
      "lng": 77.222168,
      "world": [
        182.9135416888889,
        106.71458445698778
      ],
      "politics": {
        "country": "India",
        "city": "New Delhi"
      },
      "id": 23
    },
    {
      "album": "India",
      "file": "IMG_2880.JPG",
      "date": "2013-03-23T15:20:22.000Z",
      "lat": 28.657026,
      "lng": 77.2202499,
      "world": [
        182.91217770666668,
        106.71470196179156
      ],
      "politics": {
        "country": "India",
        "city": "New Delhi"
      },
      "id": 24
    },
    {
      "album": "India",
      "file": "IMG_2960.JPG",
      "date": "2013-03-24T14:03:11.000Z",
      "lat": 28.593341,
      "lng": 77.249525,
      "world": [
        182.93299555555558,
        106.76629518829267
      ],
      "politics": {
        "country": "India",
        "city": "New Delhi"
      },
      "id": 25
    },
    {
      "album": "India",
      "file": "IMG_3001.JPG",
      "date": "2013-03-24T16:17:47.000Z",
      "lat": 28.553798,
      "lng": 77.259182,
      "world": [
        182.93986275555557,
        106.79831448801255
      ],
      "politics": {
        "country": "India",
        "city": "New Delhi"
      },
      "id": 26
    },
    {
      "album": "India",
      "file": "IMG_4078.JPG",
      "date": "2013-04-06T12:06:15.000Z",
      "lat": 29.958825,
      "lng": 78.175712,
      "world": [
        183.5916174222222,
        105.65305685846425
      ],
      "politics": {
        "country": "India",
        "city": "Haridwar"
      },
      "id": 27
    },
    {
      "album": "India",
      "file": "IMG_4385.JPG",
      "date": "2013-04-13T14:51:38.000Z",
      "lat": 19.043092,
      "lng": 72.846014,
      "world": [
        179.80160995555556,
        114.20181362834698
      ],
      "politics": {
        "country": "India",
        "city": "Mumbai"
      },
      "id": 28
    },
    {
      "album": "India",
      "file": "IMG_4626.JPG",
      "date": "2013-04-16T14:21:45.000Z",
      "lat": 9.46017,
      "lng": 76.410301,
      "world": [
        182.33621404444443,
        121.24199207522106
      ],
      "politics": {
        "country": "India",
        "city": "Chennamkary"
      },
      "id": 29
    },
    {
      "album": "India",
      "file": "IMG_4814.JPG",
      "date": "2013-04-18T11:33:07.000Z",
      "lat": 8.739054,
      "lng": 76.695345,
      "world": [
        182.538912,
        121.76132510306417
      ],
      "politics": {
        "country": "India",
        "city": "Varkala"
      },
      "id": 30
    },
    {
      "album": "India",
      "file": "IMG_5172.JPG",
      "date": "2013-04-27T10:34:39.000Z",
      "lat": 26.892447,
      "lng": 75.815681,
      "world": [
        181.91337315555555,
        108.13299755894816
      ],
      "politics": {
        "country": "India",
        "city": "Jaipur"
      },
      "id": 31
    },
    {
      "album": "India",
      "file": "IMG_5283.JPG",
      "date": "2013-04-27T13:39:29.000Z",
      "lat": 26.982398999999997,
      "lng": 75.845079,
      "world": [
        181.9342784,
        108.06124686309508
      ],
      "politics": {
        "country": "India"
      },
      "id": 32
    },
    {
      "album": "India",
      "file": "IMG_5673.JPG",
      "date": "2013-05-05T06:16:53.000Z",
      "lat": 27.173267,
      "lng": 78.042146,
      "world": [
        183.49663715555556,
        107.9088096094932
      ],
      "politics": {
        "country": "India",
        "city": "Agra"
      },
      "id": 33
    },
    {
      "album": "Burning Man",
      "file": "IMG_6249.JPG",
      "date": "2013-08-28T17:30:43.000Z",
      "lat": 40.786263,
      "lng": -119.206596,
      "world": [
        43.23086506666667,
        96.18212657820035
      ],
      "politics": {
        "country": "United States"
      },
      "id": 34
    },
    {
      "album": "Burning Man",
      "file": "IMG_6414.JPG",
      "date": "2013-08-30T13:38:58.000Z",
      "lat": 40.786263,
      "lng": -119.206596,
      "world": [
        43.23086506666667,
        96.18212657820035
      ],
      "politics": {
        "country": "United States"
      },
      "id": 35
    },
    {
      "album": "Burning Man",
      "file": "IMG_6584.JPG",
      "date": "2013-08-31T21:45:45.000Z",
      "lat": 40.786263,
      "lng": -119.206596,
      "world": [
        43.23086506666667,
        96.18212657820035
      ],
      "politics": {
        "country": "United States"
      },
      "id": 36
    },
    {
      "album": "Random",
      "file": "IMG_9969.JPG",
      "date": "2014-11-10T10:59:56.000Z",
      "lat": 13.441049,
      "lng": 103.8592989,
      "world": [
        201.85550144,
        118.35302707112254
      ],
      "politics": {
        "country": "Cambodia",
        "city": "Krong Siem Reap"
      },
      "id": 37
    },
    {
      "album": "Random",
      "file": "IMG_0023.JPG",
      "date": "2014-11-10T13:56:27.000Z",
      "lat": 13.412687,
      "lng": 103.872629,
      "world": [
        201.86498062222222,
        118.37376236034379
      ],
      "politics": {
        "country": "Cambodia",
        "city": "Krong Siem Reap"
      },
      "id": 38
    },
    {
      "album": "Random",
      "file": "IMG_0539.JPG",
      "date": "2014-11-17T21:44:53.000Z",
      "lat": 31.237133,
      "lng": 121.49025,
      "world": [
        214.39306666666667,
        104.59695401618649
      ],
      "politics": {
        "country": "China",
        "city": "Shanghai"
      },
      "id": 39
    },
    {
      "album": "Random",
      "file": "IMG_2666.JPG",
      "date": "2015-07-01T11:37:11.000Z",
      "lat": 41.006863,
      "lng": 28.977665,
      "world": [
        148.60633955555556,
        95.97459534485762
      ],
      "politics": {
        "country": "Turkey"
      },
      "id": 40
    },
    {
      "album": "Random",
      "file": "IMG_4182.JPG",
      "date": "2015-10-24T08:47:25.000Z",
      "lat": 53.893665,
      "lng": -7.848357999999999,
      "world": [
        122.41894542222222,
        82.3253813062227
      ],
      "politics": {
        "country": "Ireland",
        "city": "Mohill"
      },
      "id": 41
    }
  ],
  "albums": {
    "Europe": {
      "zoomCache": [
        [
          0,
          4,
          10,
          12,
          13
        ],
        [
          0,
          3,
          4,
          5,
          10,
          12,
          13,
          14
        ],
        [
          0,
          3,
          4,
          5,
          7,
          8,
          10,
          12,
          13,
          14
        ],
        [
          0,
          3,
          4,
          5,
          6,
          7,
          8,
          10,
          12,
          13,
          14
        ],
        [
          0,
          1,
          3,
          4,
          5,
          6,
          7,
          8,
          10,
          12,
          13,
          14
        ],
        [
          0,
          1,
          3,
          4,
          5,
          6,
          7,
          8,
          10,
          12,
          13,
          14
        ],
        [
          0,
          1,
          3,
          4,
          5,
          6,
          7,
          8,
          10,
          12,
          13,
          14
        ],
        [
          0,
          1,
          3,
          4,
          5,
          6,
          7,
          8,
          10,
          12,
          13,
          14
        ],
        [
          0,
          1,
          3,
          4,
          5,
          6,
          7,
          8,
          10,
          12,
          13,
          14
        ],
        [
          0,
          1,
          3,
          4,
          5,
          6,
          7,
          8,
          10,
          12,
          13,
          14
        ],
        [
          0,
          1,
          3,
          4,
          5,
          6,
          7,
          8,
          10,
          12,
          13,
          14
        ],
        [
          0,
          1,
          3,
          4,
          5,
          6,
          7,
          8,
          10,
          12,
          13,
          14
        ],
        [
          0,
          1,
          3,
          4,
          5,
          6,
          7,
          8,
          10,
          12,
          13,
          14
        ],
        [
          0,
          1,
          3,
          4,
          5,
          6,
          7,
          8,
          10,
          12,
          13,
          14
        ],
        [
          0,
          1,
          3,
          4,
          5,
          6,
          7,
          8,
          10,
          12,
          13,
          14
        ],
        [
          0,
          1,
          3,
          4,
          5,
          6,
          7,
          8,
          10,
          12,
          13,
          14
        ],
        [
          0,
          1,
          3,
          4,
          5,
          6,
          7,
          8,
          10,
          12,
          13,
          14
        ],
        [
          0,
          1,
          3,
          4,
          5,
          6,
          7,
          8,
          10,
          12,
          13,
          14
        ],
        [
          0,
          1,
          3,
          4,
          5,
          6,
          7,
          8,
          10,
          12,
          13,
          14
        ],
        [
          0,
          1,
          3,
          4,
          5,
          6,
          7,
          8,
          10,
          12,
          13,
          14
        ]
      ],
      "noGPS": [],
      "boundingBox": {
        "minLat": 40.750153,
        "maxLat": 59.327995,
        "minLng": -3.1917,
        "maxLng": 18.073475
      },
      "records": [
        0,
        1,
        3,
        4,
        5,
        6,
        7,
        8,
        10,
        12,
        13,
        14
      ]
    },
    "Random": {
      "zoomCache": [
        [
          2,
          9,
          11,
          15,
          16,
          37,
          39,
          40,
          41
        ],
        [
          2,
          9,
          11,
          15,
          16,
          17,
          37,
          39,
          40,
          41
        ],
        [
          2,
          9,
          11,
          15,
          16,
          17,
          37,
          39,
          40,
          41
        ],
        [
          2,
          9,
          11,
          15,
          16,
          17,
          37,
          39,
          40,
          41
        ],
        [
          2,
          9,
          11,
          15,
          16,
          17,
          37,
          39,
          40,
          41
        ],
        [
          2,
          9,
          11,
          15,
          16,
          17,
          37,
          39,
          40,
          41
        ],
        [
          2,
          9,
          11,
          15,
          16,
          17,
          37,
          39,
          40,
          41
        ],
        [
          2,
          9,
          11,
          15,
          16,
          17,
          37,
          39,
          40,
          41
        ],
        [
          2,
          9,
          11,
          15,
          16,
          17,
          37,
          39,
          40,
          41
        ],
        [
          2,
          9,
          11,
          15,
          16,
          17,
          37,
          38,
          39,
          40,
          41
        ],
        [
          2,
          9,
          11,
          15,
          16,
          17,
          37,
          38,
          39,
          40,
          41
        ],
        [
          2,
          9,
          11,
          15,
          16,
          17,
          37,
          38,
          39,
          40,
          41
        ],
        [
          2,
          9,
          11,
          15,
          16,
          17,
          37,
          38,
          39,
          40,
          41
        ],
        [
          2,
          9,
          11,
          15,
          16,
          17,
          37,
          38,
          39,
          40,
          41
        ],
        [
          2,
          9,
          11,
          15,
          16,
          17,
          37,
          38,
          39,
          40,
          41
        ],
        [
          2,
          9,
          11,
          15,
          16,
          17,
          37,
          38,
          39,
          40,
          41
        ],
        [
          2,
          9,
          11,
          15,
          16,
          17,
          37,
          38,
          39,
          40,
          41
        ],
        [
          2,
          9,
          11,
          15,
          16,
          17,
          37,
          38,
          39,
          40,
          41
        ],
        [
          2,
          9,
          11,
          15,
          16,
          17,
          37,
          38,
          39,
          40,
          41
        ],
        [
          2,
          9,
          11,
          15,
          16,
          17,
          37,
          38,
          39,
          40,
          41
        ]
      ],
      "noGPS": [],
      "boundingBox": {
        "minLat": -25.681496000000003,
        "maxLat": 53.893665,
        "minLng": -72.545197,
        "maxLng": 121.49025
      },
      "records": [
        2,
        9,
        11,
        15,
        16,
        17,
        37,
        38,
        39,
        40,
        41
      ]
    },
    "Thailand": {
      "zoomCache": [
        [
          18
        ],
        [
          18,
          20
        ],
        [
          18,
          20
        ],
        [
          18,
          20
        ],
        [
          18,
          20
        ],
        [
          18,
          20
        ],
        [
          18,
          20
        ],
        [
          18,
          20
        ],
        [
          18,
          20
        ],
        [
          18,
          20
        ],
        [
          18,
          19,
          20
        ],
        [
          18,
          19,
          20
        ],
        [
          18,
          19,
          20
        ],
        [
          18,
          19,
          20
        ],
        [
          18,
          19,
          20
        ],
        [
          18,
          19,
          20
        ],
        [
          18,
          19,
          20
        ],
        [
          18,
          19,
          20
        ],
        [
          18,
          19,
          20
        ],
        [
          18,
          19,
          20
        ]
      ],
      "noGPS": [],
      "boundingBox": {
        "minLat": 7.741789,
        "maxLat": 18.804978,
        "minLng": 98.759575,
        "maxLng": 98.921603
      },
      "records": [
        18,
        19,
        20
      ]
    },
    "India": {
      "zoomCache": [
        [
          21,
          29,
          31
        ],
        [
          21,
          28,
          29,
          31
        ],
        [
          21,
          28,
          29,
          31
        ],
        [
          21,
          27,
          28,
          29,
          31,
          33
        ],
        [
          21,
          27,
          28,
          29,
          31,
          33
        ],
        [
          21,
          27,
          28,
          29,
          30,
          31,
          33
        ],
        [
          21,
          27,
          28,
          29,
          30,
          31,
          33
        ],
        [
          21,
          26,
          27,
          28,
          29,
          30,
          31,
          33
        ],
        [
          21,
          25,
          27,
          28,
          29,
          30,
          31,
          32,
          33
        ],
        [
          21,
          25,
          26,
          27,
          28,
          29,
          30,
          31,
          32,
          33
        ],
        [
          21,
          23,
          25,
          26,
          27,
          28,
          29,
          30,
          31,
          32,
          33
        ],
        [
          21,
          22,
          23,
          25,
          26,
          27,
          28,
          29,
          30,
          31,
          32,
          33
        ],
        [
          21,
          22,
          23,
          25,
          26,
          27,
          28,
          29,
          30,
          31,
          32,
          33
        ],
        [
          21,
          22,
          23,
          24,
          25,
          26,
          27,
          28,
          29,
          30,
          31,
          32,
          33
        ],
        [
          21,
          22,
          23,
          24,
          25,
          26,
          27,
          28,
          29,
          30,
          31,
          32,
          33
        ],
        [
          21,
          22,
          23,
          24,
          25,
          26,
          27,
          28,
          29,
          30,
          31,
          32,
          33
        ],
        [
          21,
          22,
          23,
          24,
          25,
          26,
          27,
          28,
          29,
          30,
          31,
          32,
          33
        ],
        [
          21,
          22,
          23,
          24,
          25,
          26,
          27,
          28,
          29,
          30,
          31,
          32,
          33
        ],
        [
          21,
          22,
          23,
          24,
          25,
          26,
          27,
          28,
          29,
          30,
          31,
          32,
          33
        ],
        [
          21,
          22,
          23,
          24,
          25,
          26,
          27,
          28,
          29,
          30,
          31,
          32,
          33
        ]
      ],
      "noGPS": [],
      "boundingBox": {
        "minLat": 8.739054,
        "maxLat": 29.958825,
        "minLng": 72.846014,
        "maxLng": 78.175712
      },
      "records": [
        21,
        22,
        23,
        24,
        25,
        26,
        27,
        28,
        29,
        30,
        31,
        32,
        33
      ]
    },
    "Burning Man": {
      "zoomCache": [
        [
          34
        ],
        [
          34
        ],
        [
          34
        ],
        [
          34
        ],
        [
          34
        ],
        [
          34
        ],
        [
          34
        ],
        [
          34
        ],
        [
          34
        ],
        [
          34
        ],
        [
          34
        ],
        [
          34
        ],
        [
          34
        ],
        [
          34
        ],
        [
          34
        ],
        [
          34
        ],
        [
          34
        ],
        [
          34
        ],
        [
          34
        ],
        [
          34
        ]
      ],
      "noGPS": [],
      "boundingBox": {
        "minLat": 40.786263,
        "maxLat": 40.786263,
        "minLng": -119.206596,
        "maxLng": -119.206596
      },
      "records": [
        34,
        35,
        36
      ]
    }
  },
  "countries": {
    "United Kingdom": {
      "zoomCache": [
        [
          0
        ],
        [
          0,
          3
        ],
        [
          0,
          3
        ],
        [
          0,
          3
        ],
        [
          0,
          1,
          3
        ],
        [
          0,
          1,
          3
        ],
        [
          0,
          1,
          3
        ],
        [
          0,
          1,
          3
        ],
        [
          0,
          1,
          3
        ],
        [
          0,
          1,
          3
        ],
        [
          0,
          2,
          1,
          3
        ],
        [
          0,
          2,
          1,
          3
        ],
        [
          0,
          2,
          1,
          3
        ],
        [
          0,
          2,
          11,
          1,
          3
        ],
        [
          0,
          2,
          11,
          1,
          3
        ],
        [
          0,
          2,
          11,
          1,
          3
        ],
        [
          0,
          2,
          11,
          1,
          3
        ],
        [
          0,
          2,
          11,
          1,
          3
        ],
        [
          0,
          2,
          11,
          1,
          3
        ],
        [
          0,
          2,
          11,
          1,
          3
        ]
      ],
      "noGPS": [],
      "boundingBox": {
        "minLat": 51.504307,
        "maxLat": 55.947685,
        "minLng": -3.1917,
        "maxLng": 0.131237
      },
      "Cambridge": [
        0,
        2,
        11
      ],
      "nocity": [
        1
      ],
      "Edinburgh": [
        3
      ]
    },
    "Czech Republic": {
      "zoomCache": [
        [
          4
        ],
        [
          4
        ],
        [
          4
        ],
        [
          4
        ],
        [
          4
        ],
        [
          4
        ],
        [
          4
        ],
        [
          4
        ],
        [
          4
        ],
        [
          4
        ],
        [
          4
        ],
        [
          4
        ],
        [
          4
        ],
        [
          4
        ],
        [
          4
        ],
        [
          4
        ],
        [
          4
        ],
        [
          4
        ],
        [
          4
        ],
        [
          4
        ]
      ],
      "noGPS": [],
      "boundingBox": {
        "minLat": 50.087521,
        "maxLat": 50.087521,
        "minLng": 14.420843,
        "maxLng": 14.420843
      },
      "Prague": [
        4
      ]
    },
    "Italy": {
      "zoomCache": [
        [
          5
        ],
        [
          5
        ],
        [
          5,
          7,
          8
        ],
        [
          5,
          6,
          7,
          8
        ],
        [
          5,
          6,
          7,
          8
        ],
        [
          5,
          6,
          7,
          8
        ],
        [
          5,
          6,
          7,
          8
        ],
        [
          5,
          6,
          7,
          8
        ],
        [
          5,
          6,
          7,
          8
        ],
        [
          5,
          6,
          7,
          8
        ],
        [
          5,
          6,
          7,
          8
        ],
        [
          5,
          6,
          7,
          8
        ],
        [
          5,
          6,
          7,
          8
        ],
        [
          5,
          6,
          7,
          8
        ],
        [
          5,
          6,
          7,
          8
        ],
        [
          5,
          6,
          7,
          8
        ],
        [
          5,
          6,
          7,
          8
        ],
        [
          5,
          6,
          7,
          8
        ],
        [
          5,
          6,
          7,
          8
        ],
        [
          5,
          6,
          7,
          8
        ]
      ],
      "noGPS": [],
      "boundingBox": {
        "minLat": 40.750153,
        "maxLat": 45.438061,
        "minLng": 11.255659,
        "maxLng": 14.487619
      },
      "Roma": [
        5
      ],
      "Firenze": [
        6
      ],
      "Venezia": [
        7
      ],
      "nocity": [
        8
      ]
    },
    "Malaysia": {
      "zoomCache": [
        [
          9
        ],
        [
          9
        ],
        [
          9
        ],
        [
          9
        ],
        [
          9
        ],
        [
          9
        ],
        [
          9
        ],
        [
          9
        ],
        [
          9
        ],
        [
          9
        ],
        [
          9
        ],
        [
          9
        ],
        [
          9
        ],
        [
          9
        ],
        [
          9
        ],
        [
          9
        ],
        [
          9
        ],
        [
          9
        ],
        [
          9
        ],
        [
          9
        ]
      ],
      "noGPS": [],
      "boundingBox": {
        "minLat": 3.156478,
        "maxLat": 3.156478,
        "minLng": 101.713638,
        "maxLng": 101.713638
      },
      "Kuala Lumpur": [
        9
      ]
    },
    "Sweden": {
      "zoomCache": [
        [
          10
        ],
        [
          10
        ],
        [
          10
        ],
        [
          10
        ],
        [
          10
        ],
        [
          10
        ],
        [
          10
        ],
        [
          10
        ],
        [
          10
        ],
        [
          10
        ],
        [
          10
        ],
        [
          10
        ],
        [
          10
        ],
        [
          10
        ],
        [
          10
        ],
        [
          10
        ],
        [
          10
        ],
        [
          10
        ],
        [
          10
        ],
        [
          10
        ]
      ],
      "noGPS": [],
      "boundingBox": {
        "minLat": 59.327995,
        "maxLat": 59.327995,
        "minLng": 18.073475,
        "maxLng": 18.073475
      },
      "Stockholm": [
        10
      ]
    },
    "Netherlands": {
      "zoomCache": [
        [
          12
        ],
        [
          12
        ],
        [
          12
        ],
        [
          12
        ],
        [
          12
        ],
        [
          12
        ],
        [
          12
        ],
        [
          12
        ],
        [
          12
        ],
        [
          12
        ],
        [
          12
        ],
        [
          12
        ],
        [
          12
        ],
        [
          12
        ],
        [
          12
        ],
        [
          12
        ],
        [
          12
        ],
        [
          12
        ],
        [
          12
        ],
        [
          12
        ]
      ],
      "noGPS": [],
      "boundingBox": {
        "minLat": 52.358803,
        "maxLat": 52.358803,
        "minLng": 4.883401,
        "maxLng": 4.883401
      },
      "Amsterdam": [
        12
      ]
    },
    "Spain": {
      "zoomCache": [
        [
          13
        ],
        [
          13
        ],
        [
          13
        ],
        [
          13
        ],
        [
          13
        ],
        [
          13
        ],
        [
          13
        ],
        [
          13
        ],
        [
          13
        ],
        [
          13
        ],
        [
          13
        ],
        [
          13
        ],
        [
          13
        ],
        [
          13
        ],
        [
          13
        ],
        [
          13
        ],
        [
          13
        ],
        [
          13
        ],
        [
          13
        ],
        [
          13
        ]
      ],
      "noGPS": [],
      "boundingBox": {
        "minLat": 41.391861,
        "maxLat": 41.391861,
        "minLng": 2.1650359999999997,
        "maxLng": 2.1650359999999997
      },
      "Barcelona": [
        13
      ]
    },
    "France": {
      "zoomCache": [
        [
          14
        ],
        [
          14
        ],
        [
          14
        ],
        [
          14
        ],
        [
          14
        ],
        [
          14
        ],
        [
          14
        ],
        [
          14
        ],
        [
          14
        ],
        [
          14
        ],
        [
          14
        ],
        [
          14
        ],
        [
          14
        ],
        [
          14
        ],
        [
          14
        ],
        [
          14
        ],
        [
          14
        ],
        [
          14
        ],
        [
          14
        ],
        [
          14
        ]
      ],
      "noGPS": [],
      "boundingBox": {
        "minLat": 48.858234,
        "maxLat": 48.858234,
        "minLng": 2.2945119999999997,
        "maxLng": 2.2945119999999997
      },
      "Paris": [
        14
      ]
    },
    "Peru": {
      "zoomCache": [
        [
          15
        ],
        [
          15
        ],
        [
          15
        ],
        [
          15
        ],
        [
          15
        ],
        [
          15
        ],
        [
          15
        ],
        [
          15
        ],
        [
          15
        ],
        [
          15
        ],
        [
          15
        ],
        [
          15
        ],
        [
          15
        ],
        [
          15
        ],
        [
          15
        ],
        [
          15
        ],
        [
          15
        ],
        [
          15
        ],
        [
          15
        ],
        [
          15
        ]
      ],
      "noGPS": [],
      "boundingBox": {
        "minLat": -13.164768,
        "maxLat": -13.164768,
        "minLng": -72.545197,
        "maxLng": -72.545197
      },
      "nocity": [
        15
      ]
    },
    "Brazil": {
      "zoomCache": [
        [
          16
        ],
        [
          16,
          17
        ],
        [
          16,
          17
        ],
        [
          16,
          17
        ],
        [
          16,
          17
        ],
        [
          16,
          17
        ],
        [
          16,
          17
        ],
        [
          16,
          17
        ],
        [
          16,
          17
        ],
        [
          16,
          17
        ],
        [
          16,
          17
        ],
        [
          16,
          17
        ],
        [
          16,
          17
        ],
        [
          16,
          17
        ],
        [
          16,
          17
        ],
        [
          16,
          17
        ],
        [
          16,
          17
        ],
        [
          16,
          17
        ],
        [
          16,
          17
        ],
        [
          16,
          17
        ]
      ],
      "noGPS": [],
      "boundingBox": {
        "minLat": -25.681496000000003,
        "maxLat": -22.752811,
        "minLng": -54.440872,
        "maxLng": -41.884169
      },
      "Foz do Iguaçu": [
        16
      ],
      "Armação dos Búzios": [
        17
      ]
    },
    "Thailand": {
      "zoomCache": [
        [
          18
        ],
        [
          18,
          20
        ],
        [
          18,
          20
        ],
        [
          18,
          20
        ],
        [
          18,
          20
        ],
        [
          18,
          20
        ],
        [
          18,
          20
        ],
        [
          18,
          20
        ],
        [
          18,
          20
        ],
        [
          18,
          20
        ],
        [
          18,
          19,
          20
        ],
        [
          18,
          19,
          20
        ],
        [
          18,
          19,
          20
        ],
        [
          18,
          19,
          20
        ],
        [
          18,
          19,
          20
        ],
        [
          18,
          19,
          20
        ],
        [
          18,
          19,
          20
        ],
        [
          18,
          19,
          20
        ],
        [
          18,
          19,
          20
        ],
        [
          18,
          19,
          20
        ]
      ],
      "noGPS": [],
      "boundingBox": {
        "minLat": 7.741789,
        "maxLat": 18.804978,
        "minLng": 98.759575,
        "maxLng": 98.921603
      },
      "Tambon Ao Nang": [
        18,
        19
      ],
      "nocity": [
        20
      ]
    },
    "India": {
      "zoomCache": [
        [
          21,
          29,
          31
        ],
        [
          21,
          28,
          29,
          31
        ],
        [
          21,
          28,
          29,
          31
        ],
        [
          21,
          27,
          28,
          29,
          31,
          33
        ],
        [
          21,
          27,
          28,
          29,
          31,
          33
        ],
        [
          21,
          27,
          28,
          29,
          30,
          31,
          33
        ],
        [
          21,
          27,
          28,
          29,
          30,
          31,
          33
        ],
        [
          21,
          26,
          27,
          28,
          29,
          30,
          31,
          33
        ],
        [
          21,
          25,
          27,
          28,
          29,
          30,
          31,
          32,
          33
        ],
        [
          21,
          25,
          26,
          27,
          28,
          29,
          30,
          31,
          32,
          33
        ],
        [
          21,
          23,
          25,
          26,
          27,
          28,
          29,
          30,
          31,
          32,
          33
        ],
        [
          21,
          22,
          23,
          25,
          26,
          27,
          28,
          29,
          30,
          31,
          32,
          33
        ],
        [
          21,
          22,
          23,
          25,
          26,
          27,
          28,
          29,
          30,
          31,
          32,
          33
        ],
        [
          21,
          22,
          23,
          24,
          25,
          26,
          27,
          28,
          29,
          30,
          31,
          32,
          33
        ],
        [
          21,
          22,
          23,
          24,
          25,
          26,
          27,
          28,
          29,
          30,
          31,
          32,
          33
        ],
        [
          21,
          22,
          23,
          24,
          25,
          26,
          27,
          28,
          29,
          30,
          31,
          32,
          33
        ],
        [
          21,
          22,
          23,
          24,
          25,
          26,
          27,
          28,
          29,
          30,
          31,
          32,
          33
        ],
        [
          21,
          22,
          23,
          24,
          25,
          26,
          27,
          28,
          29,
          30,
          31,
          32,
          33
        ],
        [
          21,
          22,
          23,
          24,
          25,
          26,
          27,
          28,
          29,
          30,
          31,
          32,
          33
        ],
        [
          21,
          22,
          23,
          24,
          25,
          26,
          27,
          28,
          29,
          30,
          31,
          32,
          33
        ]
      ],
      "noGPS": [],
      "boundingBox": {
        "minLat": 8.739054,
        "maxLat": 29.958825,
        "minLng": 72.846014,
        "maxLng": 78.175712
      },
      "New Delhi": [
        21,
        22,
        23,
        24,
        25,
        26
      ],
      "Haridwar": [
        27
      ],
      "Mumbai": [
        28
      ],
      "Chennamkary": [
        29
      ],
      "Varkala": [
        30
      ],
      "Jaipur": [
        31
      ],
      "nocity": [
        32
      ],
      "Agra": [
        33
      ]
    },
    "United States": {
      "zoomCache": [
        [
          34
        ],
        [
          34
        ],
        [
          34
        ],
        [
          34
        ],
        [
          34
        ],
        [
          34
        ],
        [
          34
        ],
        [
          34
        ],
        [
          34
        ],
        [
          34
        ],
        [
          34
        ],
        [
          34
        ],
        [
          34
        ],
        [
          34
        ],
        [
          34
        ],
        [
          34
        ],
        [
          34
        ],
        [
          34
        ],
        [
          34
        ],
        [
          34
        ]
      ],
      "noGPS": [],
      "boundingBox": {
        "minLat": 40.786263,
        "maxLat": 40.786263,
        "minLng": -119.206596,
        "maxLng": -119.206596
      },
      "nocity": [
        34,
        35,
        36
      ]
    },
    "Cambodia": {
      "zoomCache": [
        [
          37
        ],
        [
          37
        ],
        [
          37
        ],
        [
          37
        ],
        [
          37
        ],
        [
          37
        ],
        [
          37
        ],
        [
          37
        ],
        [
          37
        ],
        [
          37,
          38
        ],
        [
          37,
          38
        ],
        [
          37,
          38
        ],
        [
          37,
          38
        ],
        [
          37,
          38
        ],
        [
          37,
          38
        ],
        [
          37,
          38
        ],
        [
          37,
          38
        ],
        [
          37,
          38
        ],
        [
          37,
          38
        ],
        [
          37,
          38
        ]
      ],
      "noGPS": [],
      "boundingBox": {
        "minLat": 13.412687,
        "maxLat": 13.441049,
        "minLng": 103.8592989,
        "maxLng": 103.872629
      },
      "Krong Siem Reap": [
        37,
        38
      ]
    },
    "China": {
      "zoomCache": [
        [
          39
        ],
        [
          39
        ],
        [
          39
        ],
        [
          39
        ],
        [
          39
        ],
        [
          39
        ],
        [
          39
        ],
        [
          39
        ],
        [
          39
        ],
        [
          39
        ],
        [
          39
        ],
        [
          39
        ],
        [
          39
        ],
        [
          39
        ],
        [
          39
        ],
        [
          39
        ],
        [
          39
        ],
        [
          39
        ],
        [
          39
        ],
        [
          39
        ]
      ],
      "noGPS": [],
      "boundingBox": {
        "minLat": 31.237133,
        "maxLat": 31.237133,
        "minLng": 121.49025,
        "maxLng": 121.49025
      },
      "Shanghai": [
        39
      ]
    },
    "Turkey": {
      "zoomCache": [
        [
          40
        ],
        [
          40
        ],
        [
          40
        ],
        [
          40
        ],
        [
          40
        ],
        [
          40
        ],
        [
          40
        ],
        [
          40
        ],
        [
          40
        ],
        [
          40
        ],
        [
          40
        ],
        [
          40
        ],
        [
          40
        ],
        [
          40
        ],
        [
          40
        ],
        [
          40
        ],
        [
          40
        ],
        [
          40
        ],
        [
          40
        ],
        [
          40
        ]
      ],
      "noGPS": [],
      "boundingBox": {
        "minLat": 41.006863,
        "maxLat": 41.006863,
        "minLng": 28.977665,
        "maxLng": 28.977665
      },
      "nocity": [
        40
      ]
    },
    "Ireland": {
      "zoomCache": [
        [
          41
        ],
        [
          41
        ],
        [
          41
        ],
        [
          41
        ],
        [
          41
        ],
        [
          41
        ],
        [
          41
        ],
        [
          41
        ],
        [
          41
        ],
        [
          41
        ],
        [
          41
        ],
        [
          41
        ],
        [
          41
        ],
        [
          41
        ],
        [
          41
        ],
        [
          41
        ],
        [
          41
        ],
        [
          41
        ],
        [
          41
        ],
        [
          41
        ]
      ],
      "noGPS": [],
      "boundingBox": {
        "minLat": 53.893665,
        "maxLat": 53.893665,
        "minLng": -7.848357999999999,
        "maxLng": -7.848357999999999
      },
      "Mohill": [
        41
      ]
    }
  }
}